{
  "name": "tables/tables-invoice-tracker",
  "category": "tables",
  "variant": "tables-invoice-tracker",
  "files": [
    {
      "path": "tables/tables-invoice-tracker/tableConfig.ts",
      "type": "registry:table-variant",
      "content": "import type { TableBuilderConfig, TableRow } from \"../../components/tables/types\";\n\nexport interface Row extends TableRow {\n  \"invoice\": string;\n  \"client\": string;\n  \"amount\": number;\n  \"tax\": number;\n  \"due\": string;\n  \"paid\": boolean;\n}\n\n\nexport const tableConfig: TableBuilderConfig = {\n  \"title\": \"Invoices\",\n  \"description\": \"Track invoices and payment status.\",\n  \"direction\": \"ltr\",\n  \"density\": \"comfortable\",\n  \"pageSize\": 8,\n  \"sortMode\": \"client\",\n  \"paginationMode\": \"client\",\n  \"expandableLayout\": \"details\",\n  \"expandableIconStyle\": \"chevron\",\n  \"expandableIconPosition\": \"first\",\n  \"paginationLayout\": \"full\",\n  \"pageSizeOptions\": [\n    5,\n    10,\n    20,\n    50,\n    100\n  ],\n  \"virtualRowHeight\": 44,\n  \"virtualMaxHeight\": 520,\n  \"enableSearch\": true,\n  \"enablePagination\": true,\n  \"enableRowSelection\": true,\n  \"enableDnD\": false,\n  \"enableColumnVisibility\": false,\n  \"enableExport\": true,\n  \"enableStriped\": true,\n  \"enableHover\": true,\n  \"enableBordered\": false,\n  \"enableStickyHeader\": false,\n  \"enableExpandableRows\": false,\n  \"enableInlineEdit\": true,\n  \"enableBulkActions\": false,\n  \"enableColumnResize\": false,\n  \"enableMultiSort\": true,\n  \"enableColumnFilters\": true,\n  \"enableRowGrouping\": false,\n  \"enableAggregation\": true,\n  \"enableFooter\": true,\n  \"columns\": [\n    {\n      \"id\": \"c1\",\n      \"key\": \"invoice\",\n      \"label\": \"Invoice #\",\n      \"type\": \"text\",\n      \"sortable\": true,\n      \"filterable\": true,\n      \"visible\": true,\n      \"align\": \"left\"\n    },\n    {\n      \"id\": \"c2\",\n      \"key\": \"client\",\n      \"label\": \"Client\",\n      \"type\": \"avatar\",\n      \"sortable\": true,\n      \"filterable\": true,\n      \"visible\": true,\n      \"align\": \"left\"\n    },\n    {\n      \"id\": \"c3\",\n      \"key\": \"amount\",\n      \"label\": \"Amount\",\n      \"type\": \"currency\",\n      \"sortable\": true,\n      \"filterable\": false,\n      \"visible\": true,\n      \"align\": \"right\",\n      \"format\": \"$\",\n      \"aggregation\": \"sum\",\n      \"footerLabel\": \"Total\"\n    },\n    {\n      \"id\": \"c4\",\n      \"key\": \"tax\",\n      \"label\": \"Tax\",\n      \"type\": \"currency\",\n      \"sortable\": true,\n      \"filterable\": false,\n      \"visible\": true,\n      \"align\": \"right\",\n      \"format\": \"$\",\n      \"aggregation\": \"sum\",\n      \"footerLabel\": \"Total\"\n    },\n    {\n      \"id\": \"c5\",\n      \"key\": \"due\",\n      \"label\": \"Due Date\",\n      \"type\": \"date\",\n      \"sortable\": true,\n      \"filterable\": false,\n      \"visible\": true,\n      \"align\": \"left\"\n    },\n    {\n      \"id\": \"c6\",\n      \"key\": \"paid\",\n      \"label\": \"Paid\",\n      \"type\": \"switch\",\n      \"sortable\": true,\n      \"filterable\": false,\n      \"visible\": true,\n      \"align\": \"center\"\n    },\n    {\n      \"id\": \"c7\",\n      \"key\": \"actions\",\n      \"label\": \"\",\n      \"type\": \"actions\",\n      \"sortable\": false,\n      \"filterable\": false,\n      \"visible\": true,\n      \"align\": \"right\"\n    }\n  ]\n} as const satisfies TableBuilderConfig;\n"
    },
    {
      "path": "tables/tables-invoice-tracker/DataTable.tsx",
      "type": "registry:table-variant",
      "content": "import { TablePreview } from \"../../components/tables/TablePreview\";\nimport { tableConfig, type Row } from \"./tableConfig\";\nimport { useRowInteractions } from \"./useRowInteractions\";\n\ninterface DataTableProps {\n  data: Row[];\n}\n\nexport default function InvoiceTrackerTable({ data }: DataTableProps) {\n  // Typed per-column change handlers — see useRowInteractions.ts.\n  // Pass `onCellInteract` to TablePreview to route user edits through your logic.\n  const { onCellInteract } = useRowInteractions<Row>();\n\n  return <TablePreview config={tableConfig} data={data} onCellInteract={onCellInteract} />;\n}\n"
    },
    {
      "path": "tables/tables-invoice-tracker/useRowInteractions.ts",
      "type": "registry:table-variant",
      "content": "import { useCallback } from \"react\";\nimport type { Row } from \"./tableConfig\";\n\n/**\n * Per-column user-interaction handlers for this DataTable.\n *\n * One handler per interactive column (dropdown / switch / radio / checkbox /\n * rating). Each receives the full row plus the old and new values so you\n * can react with full context — no extra lookups, no stale closures:\n *\n *   onPaidChange(row, oldValue, newValue)  ← \"Paid\" (switch)\n *\n * The hook also exposes a single `onCellInteract(row, key, oldValue, newValue)`\n * dispatcher you can pass straight to <TablePreview onCellInteract={...} />\n * — its signature matches the engine prop exactly and routes each cell\n * change to the matching typed handler above.\n */\nexport interface UseRowInteractions<TRow extends { id: string }> {\n  onPaidChange: (row: TRow, oldValue: boolean, newValue: boolean) => Promise<void>;\n  /**\n   * Engine-compatible dispatcher. Signature matches `TablePreviewProps['onCellInteract']`\n   * positional argument order: (row, key, oldValue, newValue).\n   */\n  onCellInteract: (\n    row: Record<string, unknown>,\n    key: string,\n    oldValue: unknown,\n    newValue: unknown,\n  ) => Promise<void> | void;\n}\n\nexport function useRowInteractions<TRow extends { id: string } = Row>(): UseRowInteractions<TRow> {\n  /**\n   * Fires when the user changes the \"Paid\" cell (type: switch).\n   * Replace the body with your own logic — call an API, dispatch an action,\n   * trigger analytics, persist to a store, etc. The full row is passed in\n   * so you have id + every other column value without an extra lookup.\n   */\n  const onPaidChange = useCallback(async (\n    row: TRow,\n    oldValue: boolean,\n    newValue: boolean,\n  ): Promise<void> => {\n    if (oldValue === newValue) return;\n    // eslint-disable-next-line no-console\n    console.log(\"[onPaidChange]\", { rowId: row.id, oldValue, newValue, row });\n    // TODO: e.g. await fetch(`/api/rows/${row.id}`, {\n    //   method: \"PATCH\",\n    //   headers: { \"Content-Type\": \"application/json\" },\n    //   body: JSON.stringify({ \"paid\": newValue }),\n    // });\n  }, []);\n\n  const onCellInteract = useCallback((\n    row: Record<string, unknown>,\n    key: string,\n    oldValue: unknown,\n    newValue: unknown,\n  ): Promise<void> | void => {\n    switch (key) {\n      case \"paid\":\n        return onPaidChange(row as TRow, oldValue as boolean, newValue as boolean);\n      default:\n        return;\n    }\n  }, [onPaidChange]);\n\n  return {\n    onCellInteract,\n    onPaidChange,\n  };\n}\n"
    }
  ]
}