{
  "name": "charts/polar-area/gradient",
  "category": "charts",
  "variant": "polar-area/gradient",
  "files": [
    {
      "path": "charts/polar-area/gradientChart.tsx",
      "type": "registry:variant",
      "content": "import { PolarAreaChart } from \"../../components/charts/polar-area\";\n\nconst data = \"North\\n55\\nEast\\n70\\nSouth\\n42\\nWest\\n63\";\n\nexport default function PolarAreaChartGradientExample() {\n  return <PolarAreaChart data={data} variant=\"gradient\" title=\"Gradient\" />;\n}"
    }
  ]
}