{
  "name": "charts/bump/smooth",
  "category": "charts",
  "variant": "bump/smooth",
  "files": [
    {
      "path": "charts/bump/smoothChart.tsx",
      "type": "registry:variant",
      "content": "import { BumpChart } from \"../../components/charts/bump\";\n\nconst data = [{\"label\":\"Alpha\",\"value\":95},{\"label\":\"Beta\",\"value\":72},{\"label\":\"Gamma\",\"value\":88},{\"label\":\"Delta\",\"value\":56},{\"label\":\"Epsilon\",\"value\":81}];\n\nexport default function BumpChartSmoothExample() {\n  return <BumpChart data={data} variant=\"smooth\" title=\"Smooth\" />;\n}"
    }
  ]
}